cp/__init__.py
continuous_pull-0.1.dist-info/LICENSE
continuous_pull-0.1.dist-info/METADATA
continuous_pull-0.1.dist-info/WHEEL
continuous_pull-0.1.dist-info/entry_points.txt
continuous_pull-0.1.dist-info/top_level.txt
continuous_pull-0.1.dist-info/RECORD
