Metadata-Version: 2.1
Name: continuous-pull
Version: 0.1
Summary: A lightweight CLI tool to continuously pull a Git repository.
Home-page: https://github.com/ericmjl/continuous-pull
Author: Eric J. Ma
Author-email: UNKNOWN
License: MIT
Keywords: git,utilities,command line tools,git pull,continuous pull
Platform: UNKNOWN
Requires-Dist: click (==7.0)
